ingestion_lib/__init__.py
ingestion_lib/extractors/__init__.py
ingestion_lib/extractors/base.py
ingestion_lib/extractors/flat_file.py
ingestion_lib/extractors/oracle.py
ingestion_lib/extractors/rest_api.py
ingestion_lib/extractors/sql_server.py
ingestion_lib/model/__init__.py
ingestion_lib/model/base.py
ingestion_lib/model/holman.py
ingestion_lib/provider.py
ingestion_lib/utils/__init__.py
ingestion_lib/utils/data_contract.py
ingestion_lib/utils/databricks_utils.py
ingestion_lib/utils/type_converter.py
ingestion_lib-0.0.7.dist-info/LICENSE
ingestion_lib-0.0.7.dist-info/METADATA
ingestion_lib-0.0.7.dist-info/WHEEL
ingestion_lib-0.0.7.dist-info/RECORD
