Metadata-Version: 2.1
Name: ingestion-lib
Version: 0.0.7
Summary: Library for data ingestion
License: MIT
Author: Ruslan_Mendybayev
Author-email: ruslan_mendybayev@epam.com
Requires-Python: >=3.11
Classifier: License :: OSI Approved :: MIT License
Classifier: Programming Language :: Python :: 3
Classifier: Programming Language :: Python :: 3.11
Classifier: Programming Language :: Python :: 3.12
Requires-Dist: pydantic (==1.10.6)
Requires-Dist: pyyaml (>=6.0.1)
